LICENSE
MANIFEST.in
README.md
setup.py
node_distance/__init__.py
node_distance/distances.py
node_distance/distributions.py
node_distance/extract.py
node_distance.egg-info/PKG-INFO
node_distance.egg-info/SOURCES.txt
node_distance.egg-info/dependency_links.txt
node_distance.egg-info/requires.txt
node_distance.egg-info/top_level.txt
node_distance.egg-info/zip-safe
test/__init__.py