Metadata-Version: 2.1
Name: node-distance
Version: 0.2.0
Summary: Compute distance between all nodes of a tree, and estimate an histogram that can be used as features for other models.
Home-page: http://github.com/ulf1/node-distance
Author: Ulf Hamster
Author-email: 554c46@gmail.com
License: Apache License 2.0
Platform: UNKNOWN
Requires-Python: >=3.6
License-File: LICENSE
